etltools/__init__.py
etltools/connection/__init__.py
etltools/connection/connect.py
etltools/extract/__init__.py
etltools/load/__init__.py
etltools/transform/__init__.py
etltools-0.0.2.dist-info/METADATA
etltools-0.0.2.dist-info/RECORD
etltools-0.0.2.dist-info/WHEEL
etltools-0.0.2.dist-info/top_level.txt
