Metadata-Version: 2.1
Name: etltools
Version: 0.0.2
Summary: A etl tool for DW
Home-page: https://github.com/quzhengpeng/etltools
Author: quzhengpeng
Author-email: quzhengpeng@163.com
Maintainer: quzhengpeng
Maintainer-email: quzhengpeng@163.com
License: BSD License
Platform: all
Classifier: Programming Language :: Python :: 3
Classifier: Programming Language :: Python :: 3.5
Classifier: Programming Language :: Python :: 3.6
Classifier: Programming Language :: Python :: 3.7
Classifier: Programming Language :: Python :: 3.4
Classifier: License :: OSI Approved :: MIT License
Classifier: Operating System :: OS Independent
Requires-Dist: numpy (>=1.14.3)
